FloBid/FlopsCountEngine.py
FloBid/__init__.py
FloBid/ops_tool.py
flobid-0.1.1.dist-info/METADATA
flobid-0.1.1.dist-info/WHEEL
flobid-0.1.1.dist-info/top_level.txt
flobid-0.1.1.dist-info/RECORD
