Metadata-Version: 2.4
Name: FloBid
Version: 0.1.1
Summary: Calculating the FLOPs of Forward and Backward
Author: Kunloong
Requires-Python: >=3.10
Provides-Extra: dev
Requires-Dist: torch>=2.0.0; extra == "dev"
